{
	"name": "StorageContainer",
	"properties": {
		"Name": "StorageContainer",
		"EntityType": "TABLE",
		"Namespace": {
			"DatabaseName": "lake_db"
		},
		"Description": "A component capable of storing a commodity.",
		"TableType": "EXTERNAL",
		"Origin": {
			"Type": "SPARK"
		},
		"StorageDescriptor": {
			"Columns": [
				{
					"Name": "StorageContainerId",
					"Description": "The unique identifier of a Storage Container.",
					"BaseAttributeReference": {
						"Entity": "StorageContainer.cdm.json/StorageContainer",
						"Name": "StorageContainerId"
					},
					"OriginDataTypeName": {
						"TypeName": "long",
						"IsComplexType": false,
						"IsNullable": false,
						"Properties": {
							"HIVE_TYPE_STRING": "long"
						}
					},
					"DeltaFormatInvalidMessages": []
				},
				{
					"Name": "StorageContainerTypeId",
					"Description": "The unique identifier of a storage container type.",
					"BaseAttributeReference": {
						"Entity": "StorageContainer.cdm.json/StorageContainer",
						"Name": "StorageContainerTypeId"
					},
					"OriginDataTypeName": {
						"TypeName": "integer",
						"IsComplexType": false,
						"IsNullable": true,
						"Properties": {
							"HIVE_TYPE_STRING": "integer"
						}
					},
					"DeltaFormatInvalidMessages": []
				},
				{
					"Name": "LocationId",
					"Description": "The unique identifier of a Location.",
					"BaseAttributeReference": {
						"Entity": "StorageContainer.cdm.json/StorageContainer",
						"Name": "LocationId"
					},
					"OriginDataTypeName": {
						"TypeName": "integer",
						"IsComplexType": false,
						"IsNullable": true,
						"Properties": {
							"HIVE_TYPE_STRING": "integer"
						}
					},
					"DeltaFormatInvalidMessages": []
				},
				{
					"Name": "WarehouseId",
					"Description": "The unique identifier of a Warehouse.",
					"BaseAttributeReference": {
						"Entity": "StorageContainer.cdm.json/StorageContainer",
						"Name": "WarehouseId"
					},
					"OriginDataTypeName": {
						"TypeName": "integer",
						"IsComplexType": false,
						"IsNullable": true,
						"Properties": {
							"HIVE_TYPE_STRING": "integer"
						}
					},
					"DeltaFormatInvalidMessages": []
				},
				{
					"Name": "StorageLength",
					"Description": "The length of the storage expressed in meters.",
					"BaseAttributeReference": {
						"Entity": "StorageContainer.cdm.json/StorageContainer",
						"Name": "StorageLength"
					},
					"OriginDataTypeName": {
						"TypeName": "decimal",
						"IsComplexType": false,
						"IsNullable": true,
						"Precision": 18,
						"Scale": 8,
						"Properties": {
							"HIVE_TYPE_STRING": "decimal"
						}
					},
					"DeltaFormatInvalidMessages": []
				},
				{
					"Name": "StorageWidth",
					"Description": "The width of the storage expressed in meters.",
					"BaseAttributeReference": {
						"Entity": "StorageContainer.cdm.json/StorageContainer",
						"Name": "StorageWidth"
					},
					"OriginDataTypeName": {
						"TypeName": "decimal",
						"IsComplexType": false,
						"IsNullable": true,
						"Precision": 18,
						"Scale": 8,
						"Properties": {
							"HIVE_TYPE_STRING": "decimal"
						}
					},
					"DeltaFormatInvalidMessages": []
				},
				{
					"Name": "StorageHeight",
					"Description": "The height of the storage expressed in meters.",
					"BaseAttributeReference": {
						"Entity": "StorageContainer.cdm.json/StorageContainer",
						"Name": "StorageHeight"
					},
					"OriginDataTypeName": {
						"TypeName": "decimal",
						"IsComplexType": false,
						"IsNullable": true,
						"Precision": 18,
						"Scale": 8,
						"Properties": {
							"HIVE_TYPE_STRING": "decimal"
						}
					},
					"DeltaFormatInvalidMessages": []
				},
				{
					"Name": "StorageShellThickness",
					"Description": "The thickness of the storage expressed in millimeters.",
					"BaseAttributeReference": {
						"Entity": "StorageContainer.cdm.json/StorageContainer",
						"Name": "StorageShellThickness"
					},
					"OriginDataTypeName": {
						"TypeName": "integer",
						"IsComplexType": false,
						"IsNullable": true,
						"Properties": {
							"HIVE_TYPE_STRING": "integer"
						}
					},
					"DeltaFormatInvalidMessages": []
				},
				{
					"Name": "CycleRate",
					"Description": "The Cycle rate is the average number of times a reservoir's working gas volume can be turned over during a specific period of time.",
					"BaseAttributeReference": {
						"Entity": "StorageContainer.cdm.json/StorageContainer",
						"Name": "CycleRate"
					},
					"OriginDataTypeName": {
						"TypeName": "integer",
						"IsComplexType": false,
						"IsNullable": true,
						"Properties": {
							"HIVE_TYPE_STRING": "integer"
						}
					},
					"DeltaFormatInvalidMessages": []
				},
				{
					"Name": "CycleRateUnitOfMeasureId",
					"Description": "The unique identifier of a Unit Of Measure.",
					"BaseAttributeReference": {
						"Entity": "StorageContainer.cdm.json/StorageContainer",
						"Name": "CycleRateUnitOfMeasureId"
					},
					"OriginDataTypeName": {
						"TypeName": "integer",
						"IsComplexType": false,
						"IsNullable": true,
						"Properties": {
							"HIVE_TYPE_STRING": "integer"
						}
					},
					"DeltaFormatInvalidMessages": []
				},
				{
					"Name": "StorageContainerNote",
					"Description": "A note, comment or additional information regarding the storage container.",
					"BaseAttributeReference": {
						"Entity": "StorageContainer.cdm.json/StorageContainer",
						"Name": "StorageContainerNote"
					},
					"OriginDataTypeName": {
						"TypeName": "string",
						"IsComplexType": false,
						"IsNullable": true,
						"Length": 2048,
						"Properties": {
							"HIVE_TYPE_STRING": "string"
						}
					},
					"DeltaFormatInvalidMessages": []
				},
				{
					"Name": "ShippingLocationId",
					"Description": "The unique identifier of a Shipping Location.",
					"BaseAttributeReference": {
						"Entity": "StorageContainer.cdm.json/StorageContainer",
						"Name": "ShippingLocationId"
					},
					"OriginDataTypeName": {
						"TypeName": "integer",
						"IsComplexType": false,
						"IsNullable": true,
						"Properties": {
							"HIVE_TYPE_STRING": "integer"
						}
					},
					"DeltaFormatInvalidMessages": []
				}
			],
			"Properties": {
				"textinputformat.record.delimiter": ",",
				"compression": "",
				"derivedModelAttributeInfo": "{\"attributeReferences\":{\"StorageContainerId\":{\"entity\":\"StorageContainer.cdm.json/StorageContainer\",\"name\":\"StorageContainerId\"},\"StorageContainerTypeId\":{\"entity\":\"StorageContainer.cdm.json/StorageContainer\",\"name\":\"StorageContainerTypeId\"},\"LocationId\":{\"entity\":\"StorageContainer.cdm.json/StorageContainer\",\"name\":\"LocationId\"},\"WarehouseId\":{\"entity\":\"StorageContainer.cdm.json/StorageContainer\",\"name\":\"WarehouseId\"},\"StorageLength\":{\"entity\":\"StorageContainer.cdm.json/StorageContainer\",\"name\":\"StorageLength\"},\"StorageWidth\":{\"entity\":\"StorageContainer.cdm.json/StorageContainer\",\"name\":\"StorageWidth\"},\"StorageHeight\":{\"entity\":\"StorageContainer.cdm.json/StorageContainer\",\"name\":\"StorageHeight\"},\"StorageShellThickness\":{\"entity\":\"StorageContainer.cdm.json/StorageContainer\",\"name\":\"StorageShellThickness\"},\"CycleRate\":{\"entity\":\"StorageContainer.cdm.json/StorageContainer\",\"name\":\"CycleRate\"},\"CycleRateUnitOfMeasureId\":{\"entity\":\"StorageContainer.cdm.json/StorageContainer\",\"name\":\"CycleRateUnitOfMeasureId\"},\"StorageContainerNote\":{\"entity\":\"StorageContainer.cdm.json/StorageContainer\",\"name\":\"StorageContainerNote\"},\"ShippingLocationId\":{\"entity\":\"StorageContainer.cdm.json/StorageContainer\",\"name\":\"ShippingLocationId\"}}}"
			},
			"Compressed": false,
			"IsStoredAsSubdirectories": false
		},
		"Properties": {
			"DerivedModelEntityInfo": "{\"entityDirectives\":{\"baseEntityReference\":{\"name\":\"StorageContainer\",\"path\":\"StorageContainer.cdm.json/StorageContainer\"},\"description\":\"A component capable of storing a commodity.\",\"primaryKey\":[\"StorageContainerId\"],\"projectionInfo\":{\"attributes\":[{\"type\":\"Existing\",\"attributeReference\":{\"entity\":\"StorageContainer.cdm.json/StorageContainer\",\"name\":\"StorageContainerId\"},\"dataType\":\"long\",\"description\":\"The unique identifier of a Storage Container.\",\"isNullable\":false,\"name\":\"StorageContainerId\"},{\"type\":\"Existing\",\"attributeReference\":{\"entity\":\"StorageContainer.cdm.json/StorageContainer\",\"name\":\"StorageContainerTypeId\"},\"dataType\":\"integer\",\"description\":\"The unique identifier of a storage container type.\",\"isNullable\":true,\"name\":\"StorageContainerTypeId\"},{\"type\":\"Existing\",\"attributeReference\":{\"entity\":\"StorageContainer.cdm.json/StorageContainer\",\"name\":\"LocationId\"},\"dataType\":\"integer\",\"description\":\"The unique identifier of a Location.\",\"isNullable\":true,\"name\":\"LocationId\"},{\"type\":\"Existing\",\"attributeReference\":{\"entity\":\"StorageContainer.cdm.json/StorageContainer\",\"name\":\"WarehouseId\"},\"dataType\":\"integer\",\"description\":\"The unique identifier of a Warehouse.\",\"isNullable\":true,\"name\":\"WarehouseId\"},{\"type\":\"Existing\",\"attributeReference\":{\"entity\":\"StorageContainer.cdm.json/StorageContainer\",\"name\":\"StorageLength\"},\"dataType\":\"decimal\",\"dataTypeLength\":18,\"description\":\"The length of the storage expressed in meters.\",\"isNullable\":true,\"scale\":8,\"name\":\"StorageLength\"},{\"type\":\"Existing\",\"attributeReference\":{\"entity\":\"StorageContainer.cdm.json/StorageContainer\",\"name\":\"StorageWidth\"},\"dataType\":\"decimal\",\"dataTypeLength\":18,\"description\":\"The width of the storage expressed in meters.\",\"isNullable\":true,\"scale\":8,\"name\":\"StorageWidth\"},{\"type\":\"Existing\",\"attributeReference\":{\"entity\":\"StorageContainer.cdm.json/StorageContainer\",\"name\":\"StorageHeight\"},\"dataType\":\"decimal\",\"dataTypeLength\":18,\"description\":\"The height of the storage expressed in meters.\",\"isNullable\":true,\"scale\":8,\"name\":\"StorageHeight\"},{\"type\":\"Existing\",\"attributeReference\":{\"entity\":\"StorageContainer.cdm.json/StorageContainer\",\"name\":\"StorageShellThickness\"},\"dataType\":\"integer\",\"description\":\"The thickness of the storage expressed in millimeters.\",\"isNullable\":true,\"name\":\"StorageShellThickness\"},{\"type\":\"Existing\",\"attributeReference\":{\"entity\":\"StorageContainer.cdm.json/StorageContainer\",\"name\":\"CycleRate\"},\"dataType\":\"integer\",\"description\":\"The Cycle rate is the average number of times a reservoir's working gas volume can be turned over during a specific period of time.\",\"isNullable\":true,\"name\":\"CycleRate\"},{\"type\":\"Existing\",\"attributeReference\":{\"entity\":\"StorageContainer.cdm.json/StorageContainer\",\"name\":\"CycleRateUnitOfMeasureId\"},\"dataType\":\"integer\",\"description\":\"The unique identifier of a Unit Of Measure.\",\"isNullable\":true,\"name\":\"CycleRateUnitOfMeasureId\"},{\"type\":\"Existing\",\"attributeReference\":{\"entity\":\"StorageContainer.cdm.json/StorageContainer\",\"name\":\"StorageContainerNote\"},\"dataType\":\"string\",\"dataTypeLength\":2048,\"description\":\"A note, comment or additional information regarding the storage container.\",\"isNullable\":true,\"name\":\"StorageContainerNote\"},{\"type\":\"Existing\",\"attributeReference\":{\"entity\":\"StorageContainer.cdm.json/StorageContainer\",\"name\":\"ShippingLocationId\"},\"dataType\":\"integer\",\"description\":\"The unique identifier of a Shipping Location.\",\"isNullable\":true,\"name\":\"ShippingLocationId\"}]}}}",
			"Description": "A component capable of storing a commodity.",
			"DisplayFolderInfo": "{\"name\":\"Network\",\"colorCode\":\"#0050AC\"}",
			"PrimaryKeys": "StorageContainerId"
		},
		"Retention": 0,
		"Temporary": false,
		"IsRewriteEnabled": false
	},
	"type": "TABLE"
}